odoo/addons/base_queued_notify/README.rst
odoo/addons/base_queued_notify/__init__.py
odoo/addons/base_queued_notify/__manifest__.py
odoo/addons/base_queued_notify/i18n/es.po
odoo/addons/base_queued_notify/models/__init__.py
odoo/addons/base_queued_notify/models/activity_notify_mixin.py
odoo/addons/base_queued_notify/models/mail_notify_mixin.py
odoo/addons/base_queued_notify/models/note_notify_mixin.py
odoo/addons/base_queued_notify/models/notify_mixin.py
odoo/addons/base_queued_notify/readme/CONTRIBUTORS.md
odoo/addons/base_queued_notify/readme/DESCRIPTION.md
odoo/addons/base_queued_notify/readme/ROADMAP.md
odoo/addons/base_queued_notify/readme/USAGE.md
odoo/addons/base_queued_notify/static/description/icon.png
odoo/addons/base_queued_notify/static/description/index.html
odoo/addons/base_queued_notify/tests/__init__.py
odoo/addons/base_queued_notify/tests/common.py
odoo/addons/base_queued_notify/views/base_queued_notify_views.xml
odoo_addon_base_queued_notify-17.0.1.0.0.1.dist-info/METADATA
odoo_addon_base_queued_notify-17.0.1.0.0.1.dist-info/WHEEL
odoo_addon_base_queued_notify-17.0.1.0.0.1.dist-info/top_level.txt
odoo_addon_base_queued_notify-17.0.1.0.0.1.dist-info/RECORD
